fred/__init__.py
fred/_util/__init__.py
fred/_util/cli.py
fred/_util/decorators.py
fred/api/__init__.py
fred/api/_fred_client.py
fred/api/categories.py
fred/api/exceptions.py
fred/api/releases.py
fred/api/series.py
fred/api/sources.py
fred/api/tags.py
fred/cli/__init__.py
fred/cli/__main__.py
fred/cli/categories.py
fred/cli/releases.py
fred/cli/series.py
fred/cli/sources.py
fred/cli/tags.py
fred_py_api-1.2.0.dist-info/LICENSE
fred_py_api-1.2.0.dist-info/METADATA
fred_py_api-1.2.0.dist-info/WHEEL
fred_py_api-1.2.0.dist-info/entry_points.txt
fred_py_api-1.2.0.dist-info/top_level.txt
fred_py_api-1.2.0.dist-info/RECORD
