Metadata-Version: 2.1
Name: fred-py-api
Version: 1.2.0
Summary: A fully featured FRED Command Line Interface & Python API client library.
Author-email: Zachary Spar <zachspar@gmail.com>
Project-URL: Homepage, https://github.com/zachspar/fred_py_api
Project-URL: Bug Tracker, https://github.com/zachspar/fred_py_api/issues
Classifier: Development Status :: 5 - Production/Stable
Classifier: Intended Audience :: Developers
Classifier: Intended Audience :: Financial and Insurance Industry
Classifier: Intended Audience :: Science/Research
Classifier: Programming Language :: Python :: 3.6
Classifier: Programming Language :: Python :: 3.7
Classifier: Programming Language :: Python :: 3.8
Classifier: Programming Language :: Python :: 3.9
Classifier: Programming Language :: Python :: 3.10
Classifier: Programming Language :: Python :: 3.11
Classifier: Programming Language :: Python :: 3.12
Classifier: License :: OSI Approved :: MIT License
Classifier: Operating System :: OS Independent
Requires-Python: >=3.6
License-File: LICENSE
Requires-Dist: requests >=2.17.3
Requires-Dist: click >=7.0
Provides-Extra: ci
Requires-Dist: black ==22.6.0 ; extra == 'ci'
Requires-Dist: coverage ==6.4.2 ; extra == 'ci'
Provides-Extra: dev
Requires-Dist: black ==22.6.0 ; extra == 'dev'
Requires-Dist: coverage ==6.4.2 ; extra == 'dev'
Requires-Dist: tox ==3.25.1 ; extra == 'dev'
Requires-Dist: sphinx ==7.2.6 ; extra == 'dev'
